setup.py
nbconvert_watch/__init__.py
nbconvert_watch/command_line.py
nbconvert_watch/utils.py
nbconvert_watch.egg-info/PKG-INFO
nbconvert_watch.egg-info/SOURCES.txt
nbconvert_watch.egg-info/dependency_links.txt
nbconvert_watch.egg-info/entry_points.txt
nbconvert_watch.egg-info/not-zip-safe
nbconvert_watch.egg-info/requires.txt
nbconvert_watch.egg-info/top_level.txt