Metadata-Version: 1.0
Name: nbconvert-watch
Version: 0.2.3
Summary: Monitor Jupyter notebooks and run them automatically
Home-page: https://github.com/APLmath/nbconvert_watch
Author: Andrew Lee
Author-email: andrew.lee.cal@gmail.com
License: MIT
Platform: UNKNOWN
